{"attributes":{"backlinks":[],"path":"/home/lorenz/.julia/dev/Pollen/src/rewriters/backlinks.jl","package_id":"Pollen@localdeploy","title":"Pollen/rewriters/backlinks.jl","module_id":"Pollen"},"tag":"sourcefile","children":[{"attributes":{},"tag":"julia","children":[{"attributes":{"lang":"julia"},"tag":"codeblock","children":[{"attributes":{},"tag":"julia","children":[{"attributes":{},"tag":"struct","children":[{"attributes":{},"tag":"false","children":[""],"type":"node"},{"attributes":{},"tag":"struct","children":["struct"],"type":"node"},{"attributes":{},"tag":"<:","children":[{"attributes":{},"tag":"Whitespace","children":[" "],"type":"node"},{"attributes":{"reftype":"symbol","document_id":"Pollen@localdeploy/ref/Pollen.Backlinks"},"tag":"reference","children":["Backlinks"],"type":"node"},{"attributes":{},"tag":"Whitespace","children":[" "],"type":"node"},{"attributes":{},"tag":"<:","children":["<:"],"type":"node"},{"attributes":{},"tag":"Whitespace","children":[" "],"type":"node"},{"attributes":{"reftype":"symbol","document_id":"Pollen@localdeploy/ref/Pollen.Rewriter"},"tag":"reference","children":["Rewriter"],"type":"node"}],"type":"node"},{"attributes":{},"tag":"block","children":[{"attributes":{},"tag":"NewlineWs","children":["\n    "],"type":"node"},{"attributes":{},"tag":"::","children":[{"attributes":{},"tag":"Identifier","children":["graph"],"type":"node"},{"attributes":{},"tag":"::","children":["::"],"type":"node"},{"attributes":{},"tag":"Identifier","children":["Any"],"type":"node"}],"type":"node"},{"attributes":{},"tag":"NewlineWs","children":["\n"],"type":"node"}],"type":"node"},{"attributes":{},"tag":"end","children":["end"],"type":"node"}],"type":"node"},{"attributes":{},"tag":"NewlineWs","children":["\n"],"type":"node"},{"attributes":{},"tag":"NewlineWs","children":["\n"],"type":"node"},{"attributes":{},"tag":"macrocall","children":[{"attributes":{},"tag":"core_@doc","children":[""],"type":"node"},{"attributes":{},"tag":"string","children":[{"attributes":{},"tag":"\"\"\"","children":["\"\"\""],"type":"node"},{"attributes":{},"tag":"String","children":["\n"],"type":"node"},{"attributes":{},"tag":"String","children":["    Backlinks() <: Rewriter\n"],"type":"node"},{"attributes":{},"tag":"String","children":["\n"],"type":"node"},{"attributes":{},"tag":"String","children":["[`Rewriter`](#) that sets the `:backlinks` attribute of every page in a project\n"],"type":"node"},{"attributes":{},"tag":"String","children":["with a list of page IDs that link to it.\n"],"type":"node"},{"attributes":{},"tag":"String","children":["\n"],"type":"node"},{"attributes":{},"tag":"String","children":["A page links to another page with id `id` if it has a `Node(:reference, ...)`\n"],"type":"node"},{"attributes":{},"tag":"String","children":["with attribute `:document_id = id`. See [`ResolveReferences`](#) and [`ResolveSymbols`](#)\n"],"type":"node"},{"attributes":{},"tag":"String","children":["for rewriters that create nodes with `:reference` tags.\n"],"type":"node"},{"attributes":{},"tag":"\"\"\"","children":["\"\"\""],"type":"node"}],"type":"node"},{"attributes":{},"tag":"NewlineWs","children":["\n"],"type":"node"},{"attributes":{},"tag":"function","children":[{"attributes":{},"tag":"function","children":["function"],"type":"node"},{"attributes":{},"tag":"Whitespace","children":[" "],"type":"node"},{"attributes":{},"tag":"call","children":[{"attributes":{"reftype":"symbol","document_id":"Pollen@localdeploy/ref/Pollen.Backlinks"},"tag":"reference","children":["Backlinks"],"type":"node"},{"attributes":{},"tag":"(","children":["("],"type":"node"},{"attributes":{},"tag":")","children":[")"],"type":"node"}],"type":"node"},{"attributes":{},"tag":"block","children":[{"attributes":{},"tag":"NewlineWs","children":["\n    "],"type":"node"},{"attributes":{},"tag":"=","children":[{"attributes":{},"tag":"Identifier","children":["g"],"type":"node"},{"attributes":{},"tag":"Whitespace","children":[" "],"type":"node"},{"attributes":{},"tag":"=","children":["="],"type":"node"},{"attributes":{},"tag":"Whitespace","children":[" "],"type":"node"},{"attributes":{},"tag":"call","children":[{"attributes":{},"tag":"Identifier","children":["MetaDiGraph"],"type":"node"},{"attributes":{},"tag":"(","children":["("],"type":"node"},{"attributes":{},"tag":"call","children":[{"attributes":{},"tag":"Identifier","children":["SimpleDiGraph"],"type":"node"},{"attributes":{},"tag":"(","children":["("],"type":"node"},{"attributes":{},"tag":"Integer","children":["0"],"type":"node"},{"attributes":{},"tag":")","children":[")"],"type":"node"}],"type":"node"},{"attributes":{},"tag":")","children":[")"],"type":"node"}],"type":"node"}],"type":"node"},{"attributes":{},"tag":"NewlineWs","children":["\n    "],"type":"node"},{"attributes":{},"tag":"call","children":[{"attributes":{},"tag":"Identifier","children":["set_prop!"],"type":"node"},{"attributes":{},"tag":"(","children":["("],"type":"node"},{"attributes":{},"tag":"Identifier","children":["g"],"type":"node"},{"attributes":{},"tag":",","children":[","],"type":"node"},{"attributes":{},"tag":"Whitespace","children":[" "],"type":"node"},{"attributes":{},"tag":"quote","children":[{"attributes":{},"tag":":","children":[":"],"type":"node"},{"attributes":{},"tag":"Identifier","children":["idxs"],"type":"node"}],"type":"node"},{"attributes":{},"tag":",","children":[","],"type":"node"},{"attributes":{},"tag":"Whitespace","children":[" "],"type":"node"},{"attributes":{},"tag":"call","children":[{"attributes":{},"tag":"curly","children":[{"attributes":{},"tag":"Identifier","children":["Dict"],"type":"node"},{"attributes":{},"tag":"{","children":["{"],"type":"node"},{"attributes":{},"tag":"Identifier","children":["String"],"type":"node"},{"attributes":{},"tag":",","children":[","],"type":"node"},{"attributes":{},"tag":"Whitespace","children":[" "],"type":"node"},{"attributes":{},"tag":"Identifier","children":["Int"],"type":"node"},{"attributes":{},"tag":"}","children":["}"],"type":"node"}],"type":"node"},{"attributes":{},"tag":"(","children":["("],"type":"node"},{"attributes":{},"tag":")","children":[")"],"type":"node"}],"type":"node"},{"attributes":{},"tag":")","children":[")"],"type":"node"}],"type":"node"},{"attributes":{},"tag":"NewlineWs","children":["\n    "],"type":"node"},{"attributes":{},"tag":"return","children":[{"attributes":{},"tag":"return","children":["return"],"type":"node"},{"attributes":{},"tag":"Whitespace","children":[" "],"type":"node"},{"attributes":{},"tag":"call","children":[{"attributes":{"reftype":"symbol","document_id":"Pollen@localdeploy/ref/Pollen.Backlinks"},"tag":"reference","children":["Backlinks"],"type":"node"},{"attributes":{},"tag":"(","children":["("],"type":"node"},{"attributes":{},"tag":"Identifier","children":["g"],"type":"node"},{"attributes":{},"tag":")","children":[")"],"type":"node"}],"type":"node"}],"type":"node"},{"attributes":{},"tag":"NewlineWs","children":["\n"],"type":"node"}],"type":"node"},{"attributes":{},"tag":"end","children":["end"],"type":"node"}],"type":"node"}],"type":"node"},{"attributes":{},"tag":"NewlineWs","children":["\n"],"type":"node"},{"attributes":{},"tag":"NewlineWs","children":["\n"],"type":"node"},{"attributes":{},"tag":"function","children":[{"attributes":{},"tag":"function","children":["function"],"type":"node"},{"attributes":{},"tag":"Whitespace","children":[" "],"type":"node"},{"attributes":{},"tag":"call","children":[{"attributes":{"reftype":"symbol","document_id":"Pollen@localdeploy/ref/Pollen.rewriteoutputs!"},"tag":"reference","children":["rewriteoutputs!"],"type":"node"},{"attributes":{},"tag":"(","children":["("],"type":"node"},{"attributes":{},"tag":"Identifier","children":["docdict"],"type":"node"},{"attributes":{},"tag":",","children":[","],"type":"node"},{"attributes":{},"tag":"Whitespace","children":[" "],"type":"node"},{"attributes":{},"tag":"::","children":[{"attributes":{},"tag":"Identifier","children":["docgraph"],"type":"node"},{"attributes":{},"tag":"::","children":["::"],"type":"node"},{"attributes":{"reftype":"symbol","document_id":"Pollen@localdeploy/ref/Pollen.Backlinks"},"tag":"reference","children":["Backlinks"],"type":"node"}],"type":"node"},{"attributes":{},"tag":")","children":[")"],"type":"node"}],"type":"node"},{"attributes":{},"tag":"block","children":[{"attributes":{},"tag":"NewlineWs","children":["\n    "],"type":"node"},{"attributes":{},"tag":"=","children":[{"attributes":{},"tag":"Identifier","children":["g"],"type":"node"},{"attributes":{},"tag":"Whitespace","children":[" "],"type":"node"},{"attributes":{},"tag":"=","children":["="],"type":"node"},{"attributes":{},"tag":"Whitespace","children":[" "],"type":"node"},{"attributes":{},"tag":".","children":[{"attributes":{},"tag":"Identifier","children":["docgraph"],"type":"node"},{"attributes":{},"tag":".","children":["."],"type":"node"},{"attributes":{},"tag":"quote","children":[{"attributes":{},"tag":"Identifier","children":["graph"],"type":"node"}],"type":"node"}],"type":"node"}],"type":"node"},{"attributes":{},"tag":"NewlineWs","children":["\n    "],"type":"node"},{"attributes":{},"tag":"=","children":[{"attributes":{},"tag":"Identifier","children":["idxs"],"type":"node"},{"attributes":{},"tag":"Whitespace","children":[" "],"type":"node"},{"attributes":{},"tag":"=","children":["="],"type":"node"},{"attributes":{},"tag":"Whitespace","children":[" "],"type":"node"},{"attributes":{},"tag":"call","children":[{"attributes":{},"tag":"Identifier","children":["get_prop"],"type":"node"},{"attributes":{},"tag":"(","children":["("],"type":"node"},{"attributes":{},"tag":"Identifier","children":["g"],"type":"node"},{"attributes":{},"tag":",","children":[","],"type":"node"},{"attributes":{},"tag":"Whitespace","children":[" "],"type":"node"},{"attributes":{},"tag":"quote","children":[{"attributes":{},"tag":":","children":[":"],"type":"node"},{"attributes":{},"tag":"Identifier","children":["idxs"],"type":"node"}],"type":"node"},{"attributes":{},"tag":")","children":[")"],"type":"node"}],"type":"node"}],"type":"node"},{"attributes":{},"tag":"NewlineWs","children":["\n"],"type":"node"},{"attributes":{},"tag":"NewlineWs","children":["\n    "],"type":"node"},{"attributes":{},"tag":"Comment","children":["# Add new documents to graph"],"type":"node"},{"attributes":{},"tag":"NewlineWs","children":["\n    "],"type":"node"},{"attributes":{},"tag":"for","children":[{"attributes":{},"tag":"for","children":["for"],"type":"node"},{"attributes":{},"tag":"=","children":[{"attributes":{},"tag":"Whitespace","children":[" "],"type":"node"},{"attributes":{},"tag":"tuple","children":[{"attributes":{},"tag":"(","children":["("],"type":"node"},{"attributes":{},"tag":"Identifier","children":["p"],"type":"node"},{"attributes":{},"tag":",","children":[","],"type":"node"},{"attributes":{},"tag":"Whitespace","children":[" "],"type":"node"},{"attributes":{},"tag":"Identifier","children":["doc"],"type":"node"},{"attributes":{},"tag":")","children":[")"],"type":"node"}],"type":"node"},{"attributes":{},"tag":"Whitespace","children":[" "],"type":"node"},{"attributes":{},"tag":"in","children":["in"],"type":"node"},{"attributes":{},"tag":"Whitespace","children":[" "],"type":"node"},{"attributes":{},"tag":"Identifier","children":["docdict"],"type":"node"}],"type":"node"},{"attributes":{},"tag":"block","children":[{"attributes":{},"tag":"NewlineWs","children":["\n        "],"type":"node"},{"attributes":{},"tag":"=","children":[{"attributes":{},"tag":"Identifier","children":["name"],"type":"node"},{"attributes":{},"tag":"Whitespace","children":[" "],"type":"node"},{"attributes":{},"tag":"=","children":["="],"type":"node"},{"attributes":{},"tag":"Whitespace","children":[" "],"type":"node"},{"attributes":{},"tag":"call","children":[{"attributes":{},"tag":"Identifier","children":["string"],"type":"node"},{"attributes":{},"tag":"(","children":["("],"type":"node"},{"attributes":{},"tag":"Identifier","children":["p"],"type":"node"},{"attributes":{},"tag":")","children":[")"],"type":"node"}],"type":"node"}],"type":"node"},{"attributes":{},"tag":"NewlineWs","children":["\n        "],"type":"node"},{"attributes":{},"tag":"if","children":[{"attributes":{},"tag":"if","children":["if"],"type":"node"},{"attributes":{},"tag":"Whitespace","children":[" "],"type":"node"},{"attributes":{},"tag":"call","children":[{"attributes":{},"tag":"!","children":["!"],"type":"node"},{"attributes":{},"tag":"call","children":[{"attributes":{},"tag":"Identifier","children":["haskey"],"type":"node"},{"attributes":{},"tag":"(","children":["("],"type":"node"},{"attributes":{},"tag":"Identifier","children":["idxs"],"type":"node"},{"attributes":{},"tag":",","children":[","],"type":"node"},{"attributes":{},"tag":"Whitespace","children":[" "],"type":"node"},{"attributes":{},"tag":"Identifier","children":["name"],"type":"node"},{"attributes":{},"tag":")","children":[")"],"type":"node"}],"type":"node"}],"type":"node"},{"attributes":{},"tag":"block","children":[{"attributes":{},"tag":"NewlineWs","children":["\n            "],"type":"node"},{"attributes":{},"tag":"macrocall","children":[{"attributes":{},"tag":"@","children":["@"],"type":"node"},{"attributes":{},"tag":"MacroName","children":["assert"],"type":"node"},{"attributes":{},"tag":"Whitespace","children":[" "],"type":"node"},{"attributes":{},"tag":"call","children":[{"attributes":{},"tag":"Identifier","children":["add_vertex!"],"type":"node"},{"attributes":{},"tag":"(","children":["("],"type":"node"},{"attributes":{},"tag":"Identifier","children":["g"],"type":"node"},{"attributes":{},"tag":")","children":[")"],"type":"node"}],"type":"node"}],"type":"node"},{"attributes":{},"tag":"NewlineWs","children":["\n            "],"type":"node"},{"attributes":{},"tag":"=","children":[{"attributes":{},"tag":"Identifier","children":["v"],"type":"node"},{"attributes":{},"tag":"Whitespace","children":[" "],"type":"node"},{"attributes":{},"tag":"=","children":["="],"type":"node"},{"attributes":{},"tag":"Whitespace","children":[" "],"type":"node"},{"attributes":{},"tag":"call","children":[{"attributes":{},"tag":"Identifier","children":["nv"],"type":"node"},{"attributes":{},"tag":"(","children":["("],"type":"node"},{"attributes":{},"tag":"Identifier","children":["g"],"type":"node"},{"attributes":{},"tag":")","children":[")"],"type":"node"}],"type":"node"}],"type":"node"},{"attributes":{},"tag":"NewlineWs","children":["\n            "],"type":"node"},{"attributes":{},"tag":"=","children":[{"attributes":{},"tag":"ref","children":[{"attributes":{},"tag":"Identifier","children":["idxs"],"type":"node"},{"attributes":{},"tag":"[","children":["["],"type":"node"},{"attributes":{},"tag":"Identifier","children":["name"],"type":"node"},{"attributes":{},"tag":"]","children":["]"],"type":"node"}],"type":"node"},{"attributes":{},"tag":"Whitespace","children":[" "],"type":"node"},{"attributes":{},"tag":"=","children":["="],"type":"node"},{"attributes":{},"tag":"Whitespace","children":[" "],"type":"node"},{"attributes":{},"tag":"Identifier","children":["v"],"type":"node"}],"type":"node"},{"attributes":{},"tag":"NewlineWs","children":["\n            "],"type":"node"},{"attributes":{},"tag":"call","children":[{"attributes":{},"tag":"Identifier","children":["set_prop!"],"type":"node"},{"attributes":{},"tag":"(","children":["("],"type":"node"},{"attributes":{},"tag":"Identifier","children":["g"],"type":"node"},{"attributes":{},"tag":",","children":[","],"type":"node"},{"attributes":{},"tag":"Whitespace","children":[" "],"type":"node"},{"attributes":{},"tag":"Identifier","children":["v"],"type":"node"},{"attributes":{},"tag":",","children":[","],"type":"node"},{"attributes":{},"tag":"Whitespace","children":[" "],"type":"node"},{"attributes":{},"tag":"quote","children":[{"attributes":{},"tag":":","children":[":"],"type":"node"},{"attributes":{},"tag":"Identifier","children":["docid"],"type":"node"}],"type":"node"},{"attributes":{},"tag":",","children":[","],"type":"node"},{"attributes":{},"tag":"Whitespace","children":[" "],"type":"node"},{"attributes":{},"tag":"call","children":[{"attributes":{},"tag":"Identifier","children":["string"],"type":"node"},{"attributes":{},"tag":"(","children":["("],"type":"node"},{"attributes":{},"tag":"Identifier","children":["p"],"type":"node"},{"attributes":{},"tag":")","children":[")"],"type":"node"}],"type":"node"},{"attributes":{},"tag":")","children":[")"],"type":"node"}],"type":"node"},{"attributes":{},"tag":"NewlineWs","children":["\n            "],"type":"node"},{"attributes":{},"tag":"call","children":[{"attributes":{},"tag":"Identifier","children":["set_prop!"],"type":"node"},{"attributes":{},"tag":"(","children":["("],"type":"node"},{"attributes":{},"tag":"Identifier","children":["g"],"type":"node"},{"attributes":{},"tag":",","children":[","],"type":"node"},{"attributes":{},"tag":"Whitespace","children":[" "],"type":"node"},{"attributes":{},"tag":"Identifier","children":["v"],"type":"node"},{"attributes":{},"tag":",","children":[","],"type":"node"},{"attributes":{},"tag":"Whitespace","children":[" "],"type":"node"},{"attributes":{},"tag":"quote","children":[{"attributes":{},"tag":":","children":[":"],"type":"node"},{"attributes":{},"tag":"Identifier","children":["title"],"type":"node"}],"type":"node"},{"attributes":{},"tag":",","children":[","],"type":"node"},{"attributes":{},"tag":"Whitespace","children":[" "],"type":"node"},{"attributes":{},"tag":"call","children":[{"attributes":{},"tag":"Identifier","children":["get"],"type":"node"},{"attributes":{},"tag":"(","children":["("],"type":"node"},{"attributes":{},"tag":"call","children":[{"attributes":{"reftype":"symbol","document_id":"Pollen@localdeploy/ref/Pollen.attributes"},"tag":"reference","children":["attributes"],"type":"node"},{"attributes":{},"tag":"(","children":["("],"type":"node"},{"attributes":{},"tag":"Identifier","children":["doc"],"type":"node"},{"attributes":{},"tag":")","children":[")"],"type":"node"}],"type":"node"},{"attributes":{},"tag":",","children":[","],"type":"node"},{"attributes":{},"tag":"Whitespace","children":[" "],"type":"node"},{"attributes":{},"tag":"quote","children":[{"attributes":{},"tag":":","children":[":"],"type":"node"},{"attributes":{},"tag":"Identifier","children":["title"],"type":"node"}],"type":"node"},{"attributes":{},"tag":",","children":[","],"type":"node"},{"attributes":{},"tag":"Whitespace","children":[" "],"type":"node"},{"attributes":{},"tag":"call","children":[{"attributes":{},"tag":"Identifier","children":["string"],"type":"node"},{"attributes":{},"tag":"(","children":["("],"type":"node"},{"attributes":{},"tag":"Identifier","children":["v"],"type":"node"},{"attributes":{},"tag":")","children":[")"],"type":"node"}],"type":"node"},{"attributes":{},"tag":")","children":[")"],"type":"node"}],"type":"node"},{"attributes":{},"tag":")","children":[")"],"type":"node"}],"type":"node"},{"attributes":{},"tag":"NewlineWs","children":["\n            "],"type":"node"},{"attributes":{},"tag":"call","children":[{"attributes":{},"tag":"Identifier","children":["set_prop!"],"type":"node"},{"attributes":{},"tag":"(","children":["("],"type":"node"},{"attributes":{},"tag":"Identifier","children":["g"],"type":"node"},{"attributes":{},"tag":",","children":[","],"type":"node"},{"attributes":{},"tag":"Whitespace","children":[" "],"type":"node"},{"attributes":{},"tag":"Identifier","children":["v"],"type":"node"},{"attributes":{},"tag":",","children":[","],"type":"node"},{"attributes":{},"tag":"Whitespace","children":[" "],"type":"node"},{"attributes":{},"tag":"quote","children":[{"attributes":{},"tag":":","children":[":"],"type":"node"},{"attributes":{"reftype":"symbol","document_id":"Pollen@localdeploy/ref/Pollen.tag"},"tag":"reference","children":["tag"],"type":"node"}],"type":"node"},{"attributes":{},"tag":",","children":[","],"type":"node"},{"attributes":{},"tag":"Whitespace","children":[" "],"type":"node"},{"attributes":{},"tag":"call","children":[{"attributes":{"reftype":"symbol","document_id":"Pollen@localdeploy/ref/Pollen.tag"},"tag":"reference","children":["tag"],"type":"node"},{"attributes":{},"tag":"(","children":["("],"type":"node"},{"attributes":{},"tag":"Identifier","children":["doc"],"type":"node"},{"attributes":{},"tag":")","children":[")"],"type":"node"}],"type":"node"},{"attributes":{},"tag":")","children":[")"],"type":"node"}],"type":"node"},{"attributes":{},"tag":"NewlineWs","children":["\n        "],"type":"node"}],"type":"node"},{"attributes":{},"tag":"end","children":["end"],"type":"node"}],"type":"node"},{"attributes":{},"tag":"NewlineWs","children":["\n    "],"type":"node"}],"type":"node"},{"attributes":{},"tag":"end","children":["end"],"type":"node"}],"type":"node"},{"attributes":{},"tag":"NewlineWs","children":["\n"],"type":"node"},{"attributes":{},"tag":"NewlineWs","children":["\n    "],"type":"node"},{"attributes":{},"tag":"Comment","children":["# Add edges"],"type":"node"},{"attributes":{},"tag":"NewlineWs","children":["\n    "],"type":"node"},{"attributes":{},"tag":"for","children":[{"attributes":{},"tag":"for","children":["for"],"type":"node"},{"attributes":{},"tag":"=","children":[{"attributes":{},"tag":"Whitespace","children":[" "],"type":"node"},{"attributes":{},"tag":"tuple","children":[{"attributes":{},"tag":"(","children":["("],"type":"node"},{"attributes":{},"tag":"Identifier","children":["p"],"type":"node"},{"attributes":{},"tag":",","children":[","],"type":"node"},{"attributes":{},"tag":"Whitespace","children":[" "],"type":"node"},{"attributes":{},"tag":"Identifier","children":["doc"],"type":"node"},{"attributes":{},"tag":")","children":[")"],"type":"node"}],"type":"node"},{"attributes":{},"tag":"Whitespace","children":[" "],"type":"node"},{"attributes":{},"tag":"in","children":["in"],"type":"node"},{"attributes":{},"tag":"Whitespace","children":[" "],"type":"node"},{"attributes":{},"tag":"Identifier","children":["docdict"],"type":"node"}],"type":"node"},{"attributes":{},"tag":"block","children":[{"attributes":{},"tag":"NewlineWs","children":["\n        "],"type":"node"},{"attributes":{},"tag":"call","children":[{"attributes":{},"tag":"Identifier","children":["_addrefedges!"],"type":"node"},{"attributes":{},"tag":"(","children":["("],"type":"node"},{"attributes":{},"tag":"Identifier","children":["g"],"type":"node"},{"attributes":{},"tag":",","children":[","],"type":"node"},{"attributes":{},"tag":"Whitespace","children":[" "],"type":"node"},{"attributes":{},"tag":"Identifier","children":["doc"],"type":"node"},{"attributes":{},"tag":",","children":[","],"type":"node"},{"attributes":{},"tag":"Whitespace","children":[" "],"type":"node"},{"attributes":{},"tag":"Identifier","children":["p"],"type":"node"},{"attributes":{},"tag":")","children":[")"],"type":"node"}],"type":"node"},{"attributes":{},"tag":"NewlineWs","children":["\n    "],"type":"node"}],"type":"node"},{"attributes":{},"tag":"end","children":["end"],"type":"node"}],"type":"node"},{"attributes":{},"tag":"NewlineWs","children":["\n"],"type":"node"},{"attributes":{},"tag":"NewlineWs","children":["\n    "],"type":"node"},{"attributes":{},"tag":"for","children":[{"attributes":{},"tag":"for","children":["for"],"type":"node"},{"attributes":{},"tag":"=","children":[{"attributes":{},"tag":"Whitespace","children":[" "],"type":"node"},{"attributes":{},"tag":"tuple","children":[{"attributes":{},"tag":"(","children":["("],"type":"node"},{"attributes":{},"tag":"Identifier","children":["docid"],"type":"node"},{"attributes":{},"tag":",","children":[","],"type":"node"},{"attributes":{},"tag":"Whitespace","children":[" "],"type":"node"},{"attributes":{},"tag":"Identifier","children":["doc"],"type":"node"},{"attributes":{},"tag":")","children":[")"],"type":"node"}],"type":"node"},{"attributes":{},"tag":"Whitespace","children":[" "],"type":"node"},{"attributes":{},"tag":"in","children":["in"],"type":"node"},{"attributes":{},"tag":"Whitespace","children":[" "],"type":"node"},{"attributes":{},"tag":"Identifier","children":["docdict"],"type":"node"}],"type":"node"},{"attributes":{},"tag":"block","children":[{"attributes":{},"tag":"NewlineWs","children":["\n        "],"type":"node"},{"attributes":{},"tag":"=","children":[{"attributes":{},"tag":"Identifier","children":["v"],"type":"node"},{"attributes":{},"tag":"Whitespace","children":[" "],"type":"node"},{"attributes":{},"tag":"=","children":["="],"type":"node"},{"attributes":{},"tag":"Whitespace","children":[" "],"type":"node"},{"attributes":{},"tag":"ref","children":[{"attributes":{},"tag":"call","children":[{"attributes":{},"tag":"Identifier","children":["get_prop"],"type":"node"},{"attributes":{},"tag":"(","children":["("],"type":"node"},{"attributes":{},"tag":"Identifier","children":["g"],"type":"node"},{"attributes":{},"tag":",","children":[","],"type":"node"},{"attributes":{},"tag":"Whitespace","children":[" "],"type":"node"},{"attributes":{},"tag":"quote","children":[{"attributes":{},"tag":":","children":[":"],"type":"node"},{"attributes":{},"tag":"Identifier","children":["idxs"],"type":"node"}],"type":"node"},{"attributes":{},"tag":")","children":[")"],"type":"node"}],"type":"node"},{"attributes":{},"tag":"[","children":["["],"type":"node"},{"attributes":{},"tag":"Identifier","children":["docid"],"type":"node"},{"attributes":{},"tag":"]","children":["]"],"type":"node"}],"type":"node"}],"type":"node"},{"attributes":{},"tag":"NewlineWs","children":["\n        "],"type":"node"},{"attributes":{},"tag":"=","children":[{"attributes":{},"tag":"ref","children":[{"attributes":{},"tag":"Identifier","children":["docdict"],"type":"node"},{"attributes":{},"tag":"[","children":["["],"type":"node"},{"attributes":{},"tag":"Identifier","children":["docid"],"type":"node"},{"attributes":{},"tag":"]","children":["]"],"type":"node"}],"type":"node"},{"attributes":{},"tag":"Whitespace","children":[" "],"type":"node"},{"attributes":{},"tag":"=","children":["="],"type":"node"},{"attributes":{},"tag":"Whitespace","children":[" "],"type":"node"},{"attributes":{},"tag":"call","children":[{"attributes":{"reftype":"symbol","document_id":"Pollen@localdeploy/ref/Pollen.withattributes"},"tag":"reference","children":["withattributes"],"type":"node"},{"attributes":{},"tag":"(","children":["("],"type":"node"},{"attributes":{},"tag":"Identifier","children":["doc"],"type":"node"},{"attributes":{},"tag":",","children":[","],"type":"node"},{"attributes":{},"tag":"NewlineWs","children":["\n                                        "],"type":"node"},{"attributes":{},"tag":"call","children":[{"attributes":{},"tag":"Identifier","children":["merge"],"type":"node"},{"attributes":{},"tag":"(","children":["("],"type":"node"},{"attributes":{},"tag":"call","children":[{"attributes":{"reftype":"symbol","document_id":"Pollen@localdeploy/ref/Pollen.attributes"},"tag":"reference","children":["attributes"],"type":"node"},{"attributes":{},"tag":"(","children":["("],"type":"node"},{"attributes":{},"tag":"Identifier","children":["doc"],"type":"node"},{"attributes":{},"tag":")","children":[")"],"type":"node"}],"type":"node"},{"attributes":{},"tag":",","children":[","],"type":"node"},{"attributes":{},"tag":"NewlineWs","children":["\n                                              "],"type":"node"},{"attributes":{},"tag":"call","children":[{"attributes":{},"tag":"Identifier","children":["Dict"],"type":"node"},{"attributes":{},"tag":"(","children":["("],"type":"node"},{"attributes":{},"tag":"call","children":[{"attributes":{},"tag":"quote","children":[{"attributes":{},"tag":":","children":[":"],"type":"node"},{"attributes":{},"tag":"Identifier","children":["backlinks"],"type":"node"}],"type":"node"},{"attributes":{},"tag":"Whitespace","children":[" "],"type":"node"},{"attributes":{},"tag":"=>","children":["=>"],"type":"node"},{"attributes":{},"tag":"Whitespace","children":[" "],"type":"node"},{"attributes":{},"tag":"comprehension","children":[{"attributes":{},"tag":"[","children":["["],"type":"node"},{"attributes":{},"tag":"generator","children":[{"attributes":{},"tag":"call","children":[{"attributes":{"reftype":"symbol","document_id":"Pollen@localdeploy/ref/Pollen.backlinkdata"},"tag":"reference","children":["backlinkdata"],"type":"node"},{"attributes":{},"tag":"(","children":["("],"type":"node"},{"attributes":{},"tag":"Identifier","children":["g"],"type":"node"},{"attributes":{},"tag":",","children":[","],"type":"node"},{"attributes":{},"tag":"Whitespace","children":[" "],"type":"node"},{"attributes":{},"tag":"Identifier","children":["v_"],"type":"node"},{"attributes":{},"tag":")","children":[")"],"type":"node"}],"type":"node"},{"attributes":{},"tag":"NewlineWs","children":["\n                                                                  "],"type":"node"},{"attributes":{},"tag":"for","children":["for"],"type":"node"},{"attributes":{},"tag":"filter","children":[{"attributes":{},"tag":"=","children":[{"attributes":{},"tag":"Whitespace","children":[" "],"type":"node"},{"attributes":{},"tag":"Identifier","children":["v_"],"type":"node"},{"attributes":{},"tag":"Whitespace","children":[" "],"type":"node"},{"attributes":{},"tag":"in","children":["in"],"type":"node"},{"attributes":{},"tag":"Whitespace","children":[" "],"type":"node"},{"attributes":{},"tag":"call","children":[{"attributes":{},"tag":"Identifier","children":["inneighbors"],"type":"node"},{"attributes":{},"tag":"(","children":["("],"type":"node"},{"attributes":{},"tag":"Identifier","children":["g"],"type":"node"},{"attributes":{},"tag":",","children":[","],"type":"node"},{"attributes":{},"tag":"NewlineWs","children":["\n                                                                                        "],"type":"node"},{"attributes":{},"tag":"Identifier","children":["v"],"type":"node"},{"attributes":{},"tag":")","children":[")"],"type":"node"}],"type":"node"}],"type":"node"},{"attributes":{},"tag":"NewlineWs","children":["\n                                                                  "],"type":"node"},{"attributes":{},"tag":"if","children":["if"],"type":"node"},{"attributes":{},"tag":"call","children":[{"attributes":{},"tag":"Whitespace","children":[" "],"type":"node"},{"attributes":{},"tag":"Identifier","children":["v_"],"type":"node"},{"attributes":{},"tag":"Whitespace","children":[" "],"type":"node"},{"attributes":{},"tag":"!=","children":["!="],"type":"node"},{"attributes":{},"tag":"Whitespace","children":[" "],"type":"node"},{"attributes":{},"tag":"Identifier","children":["v"],"type":"node"}],"type":"node"}],"type":"node"}],"type":"node"},{"attributes":{},"tag":"]","children":["]"],"type":"node"}],"type":"node"}],"type":"node"},{"attributes":{},"tag":")","children":[")"],"type":"node"}],"type":"node"},{"attributes":{},"tag":")","children":[")"],"type":"node"}],"type":"node"},{"attributes":{},"tag":")","children":[")"],"type":"node"}],"type":"node"}],"type":"node"},{"attributes":{},"tag":"NewlineWs","children":["\n    "],"type":"node"}],"type":"node"},{"attributes":{},"tag":"end","children":["end"],"type":"node"}],"type":"node"},{"attributes":{},"tag":"NewlineWs","children":["\n"],"type":"node"},{"attributes":{},"tag":"NewlineWs","children":["\n    "],"type":"node"},{"attributes":{},"tag":"return","children":[{"attributes":{},"tag":"return","children":["return"],"type":"node"},{"attributes":{},"tag":"Whitespace","children":[" "],"type":"node"},{"attributes":{},"tag":"Identifier","children":["docdict"],"type":"node"}],"type":"node"},{"attributes":{},"tag":"NewlineWs","children":["\n"],"type":"node"}],"type":"node"},{"attributes":{},"tag":"end","children":["end"],"type":"node"}],"type":"node"},{"attributes":{},"tag":"NewlineWs","children":["\n"],"type":"node"},{"attributes":{},"tag":"NewlineWs","children":["\n"],"type":"node"},{"attributes":{},"tag":"function","children":[{"attributes":{},"tag":"function","children":["function"],"type":"node"},{"attributes":{},"tag":"Whitespace","children":[" "],"type":"node"},{"attributes":{},"tag":"call","children":[{"attributes":{"reftype":"symbol","document_id":"Pollen@localdeploy/ref/Pollen.backlinkdata"},"tag":"reference","children":["backlinkdata"],"type":"node"},{"attributes":{},"tag":"(","children":["("],"type":"node"},{"attributes":{},"tag":"Identifier","children":["g"],"type":"node"},{"attributes":{},"tag":",","children":[","],"type":"node"},{"attributes":{},"tag":"Whitespace","children":[" "],"type":"node"},{"attributes":{},"tag":"Identifier","children":["v_"],"type":"node"},{"attributes":{},"tag":")","children":[")"],"type":"node"}],"type":"node"},{"attributes":{},"tag":"block","children":[{"attributes":{},"tag":"NewlineWs","children":["\n    "],"type":"node"},{"attributes":{},"tag":"=","children":[{"attributes":{},"tag":"Identifier","children":["d"],"type":"node"},{"attributes":{},"tag":"Whitespace","children":[" "],"type":"node"},{"attributes":{},"tag":"=","children":["="],"type":"node"},{"attributes":{},"tag":"Whitespace","children":[" "],"type":"node"},{"attributes":{},"tag":"call","children":[{"attributes":{},"tag":"Identifier","children":["props"],"type":"node"},{"attributes":{},"tag":"(","children":["("],"type":"node"},{"attributes":{},"tag":"Identifier","children":["g"],"type":"node"},{"attributes":{},"tag":",","children":[","],"type":"node"},{"attributes":{},"tag":"Whitespace","children":[" "],"type":"node"},{"attributes":{},"tag":"Identifier","children":["v_"],"type":"node"},{"attributes":{},"tag":")","children":[")"],"type":"node"}],"type":"node"}],"type":"node"},{"attributes":{},"tag":"NewlineWs","children":["\n    "],"type":"node"},{"attributes":{},"tag":"return","children":[{"attributes":{},"tag":"return","children":["return"],"type":"node"},{"attributes":{},"tag":"Whitespace","children":[" "],"type":"node"},{"attributes":{},"tag":"Identifier","children":["d"],"type":"node"}],"type":"node"},{"attributes":{},"tag":"NewlineWs","children":["\n"],"type":"node"}],"type":"node"},{"attributes":{},"tag":"end","children":["end"],"type":"node"}],"type":"node"},{"attributes":{},"tag":"NewlineWs","children":["\n"],"type":"node"},{"attributes":{},"tag":"NewlineWs","children":["\n"],"type":"node"},{"attributes":{},"tag":"function","children":[{"attributes":{},"tag":"function","children":["function"],"type":"node"},{"attributes":{},"tag":"Whitespace","children":[" "],"type":"node"},{"attributes":{},"tag":"call","children":[{"attributes":{},"tag":"Identifier","children":["_addrefedges!"],"type":"node"},{"attributes":{},"tag":"(","children":["("],"type":"node"},{"attributes":{},"tag":"Identifier","children":["g"],"type":"node"},{"attributes":{},"tag":",","children":[","],"type":"node"},{"attributes":{},"tag":"Whitespace","children":[" "],"type":"node"},{"attributes":{},"tag":"Identifier","children":["doc"],"type":"node"},{"attributes":{},"tag":",","children":[","],"type":"node"},{"attributes":{},"tag":"Whitespace","children":[" "],"type":"node"},{"attributes":{},"tag":"Identifier","children":["path"],"type":"node"},{"attributes":{},"tag":")","children":[")"],"type":"node"}],"type":"node"},{"attributes":{},"tag":"block","children":[{"attributes":{},"tag":"NewlineWs","children":["\n    "],"type":"node"},{"attributes":{},"tag":"=","children":[{"attributes":{},"tag":"Identifier","children":["idxs"],"type":"node"},{"attributes":{},"tag":"Whitespace","children":[" "],"type":"node"},{"attributes":{},"tag":"=","children":["="],"type":"node"},{"attributes":{},"tag":"Whitespace","children":[" "],"type":"node"},{"attributes":{},"tag":"call","children":[{"attributes":{},"tag":"Identifier","children":["get_prop"],"type":"node"},{"attributes":{},"tag":"(","children":["("],"type":"node"},{"attributes":{},"tag":"Identifier","children":["g"],"type":"node"},{"attributes":{},"tag":",","children":[","],"type":"node"},{"attributes":{},"tag":"Whitespace","children":[" "],"type":"node"},{"attributes":{},"tag":"quote","children":[{"attributes":{},"tag":":","children":[":"],"type":"node"},{"attributes":{},"tag":"Identifier","children":["idxs"],"type":"node"}],"type":"node"},{"attributes":{},"tag":")","children":[")"],"type":"node"}],"type":"node"}],"type":"node"},{"attributes":{},"tag":"NewlineWs","children":["\n    "],"type":"node"},{"attributes":{},"tag":"=","children":[{"attributes":{},"tag":"Identifier","children":["v"],"type":"node"},{"attributes":{},"tag":"Whitespace","children":[" "],"type":"node"},{"attributes":{},"tag":"=","children":["="],"type":"node"},{"attributes":{},"tag":"Whitespace","children":[" "],"type":"node"},{"attributes":{},"tag":"ref","children":[{"attributes":{},"tag":"Identifier","children":["idxs"],"type":"node"},{"attributes":{},"tag":"[","children":["["],"type":"node"},{"attributes":{},"tag":"call","children":[{"attributes":{},"tag":"Identifier","children":["string"],"type":"node"},{"attributes":{},"tag":"(","children":["("],"type":"node"},{"attributes":{},"tag":"Identifier","children":["path"],"type":"node"},{"attributes":{},"tag":")","children":[")"],"type":"node"}],"type":"node"},{"attributes":{},"tag":"]","children":["]"],"type":"node"}],"type":"node"}],"type":"node"},{"attributes":{},"tag":"NewlineWs","children":["\n    "],"type":"node"},{"attributes":{},"tag":"for","children":[{"attributes":{},"tag":"for","children":["for"],"type":"node"},{"attributes":{},"tag":"=","children":[{"attributes":{},"tag":"Whitespace","children":[" "],"type":"node"},{"attributes":{},"tag":"Identifier","children":["ref"],"type":"node"},{"attributes":{},"tag":"Whitespace","children":[" "],"type":"node"},{"attributes":{},"tag":"in","children":["in"],"type":"node"},{"attributes":{},"tag":"Whitespace","children":[" "],"type":"node"},{"attributes":{},"tag":"call","children":[{"attributes":{"reftype":"symbol","document_id":"Pollen@localdeploy/ref/Pollen.select"},"tag":"reference","children":["select"],"type":"node"},{"attributes":{},"tag":"(","children":["("],"type":"node"},{"attributes":{},"tag":"Identifier","children":["doc"],"type":"node"},{"attributes":{},"tag":",","children":[","],"type":"node"},{"attributes":{},"tag":"Whitespace","children":[" "],"type":"node"},{"attributes":{},"tag":"call","children":[{"attributes":{"reftype":"symbol","document_id":"Pollen@localdeploy/ref/Pollen.SelectReference"},"tag":"reference","children":["SelectReference"],"type":"node"},{"attributes":{},"tag":"(","children":["("],"type":"node"},{"attributes":{},"tag":")","children":[")"],"type":"node"}],"type":"node"},{"attributes":{},"tag":")","children":[")"],"type":"node"}],"type":"node"}],"type":"node"},{"attributes":{},"tag":"block","children":[{"attributes":{},"tag":"NewlineWs","children":["\n        "],"type":"node"},{"attributes":{},"tag":"=","children":[{"attributes":{},"tag":"Identifier","children":["target"],"type":"node"},{"attributes":{},"tag":"Whitespace","children":[" "],"type":"node"},{"attributes":{},"tag":"=","children":["="],"type":"node"},{"attributes":{},"tag":"Whitespace","children":[" "],"type":"node"},{"attributes":{},"tag":"ref","children":[{"attributes":{},"tag":"call","children":[{"attributes":{"reftype":"symbol","document_id":"Pollen@localdeploy/ref/Pollen.attributes"},"tag":"reference","children":["attributes"],"type":"node"},{"attributes":{},"tag":"(","children":["("],"type":"node"},{"attributes":{},"tag":"Identifier","children":["ref"],"type":"node"},{"attributes":{},"tag":")","children":[")"],"type":"node"}],"type":"node"},{"attributes":{},"tag":"[","children":["["],"type":"node"},{"attributes":{},"tag":"quote","children":[{"attributes":{},"tag":":","children":[":"],"type":"node"},{"attributes":{},"tag":"Identifier","children":["document_id"],"type":"node"}],"type":"node"},{"attributes":{},"tag":"]","children":["]"],"type":"node"}],"type":"node"}],"type":"node"},{"attributes":{},"tag":"NewlineWs","children":["\n        "],"type":"node"},{"attributes":{},"tag":"=","children":[{"attributes":{},"tag":"Identifier","children":["v_"],"type":"node"},{"attributes":{},"tag":"Whitespace","children":[" "],"type":"node"},{"attributes":{},"tag":"=","children":["="],"type":"node"},{"attributes":{},"tag":"Whitespace","children":[" "],"type":"node"},{"attributes":{},"tag":"call","children":[{"attributes":{},"tag":"Identifier","children":["get"],"type":"node"},{"attributes":{},"tag":"(","children":["("],"type":"node"},{"attributes":{},"tag":"Identifier","children":["idxs"],"type":"node"},{"attributes":{},"tag":",","children":[","],"type":"node"},{"attributes":{},"tag":"Whitespace","children":[" "],"type":"node"},{"attributes":{},"tag":"call","children":[{"attributes":{},"tag":"Identifier","children":["string"],"type":"node"},{"attributes":{},"tag":"(","children":["("],"type":"node"},{"attributes":{},"tag":"Identifier","children":["target"],"type":"node"},{"attributes":{},"tag":")","children":[")"],"type":"node"}],"type":"node"},{"attributes":{},"tag":",","children":[","],"type":"node"},{"attributes":{},"tag":"Whitespace","children":[" "],"type":"node"},{"attributes":{},"tag":"Identifier","children":["nothing"],"type":"node"},{"attributes":{},"tag":")","children":[")"],"type":"node"}],"type":"node"}],"type":"node"},{"attributes":{},"tag":"NewlineWs","children":["\n        "],"type":"node"},{"attributes":{},"tag":"&&","children":[{"attributes":{},"tag":"call","children":[{"attributes":{},"tag":"Identifier","children":["isnothing"],"type":"node"},{"attributes":{},"tag":"(","children":["("],"type":"node"},{"attributes":{},"tag":"Identifier","children":["v_"],"type":"node"},{"attributes":{},"tag":")","children":[")"],"type":"node"}],"type":"node"},{"attributes":{},"tag":"Whitespace","children":[" "],"type":"node"},{"attributes":{},"tag":"&&","children":["&&"],"type":"node"},{"attributes":{},"tag":"Whitespace","children":[" "],"type":"node"},{"attributes":{},"tag":"continue","children":["continue"],"type":"node"}],"type":"node"},{"attributes":{},"tag":"NewlineWs","children":["\n        "],"type":"node"},{"attributes":{},"tag":"call","children":[{"attributes":{},"tag":"Identifier","children":["add_edge!"],"type":"node"},{"attributes":{},"tag":"(","children":["("],"type":"node"},{"attributes":{},"tag":"Identifier","children":["g"],"type":"node"},{"attributes":{},"tag":",","children":[","],"type":"node"},{"attributes":{},"tag":"Whitespace","children":[" "],"type":"node"},{"attributes":{},"tag":"Identifier","children":["v"],"type":"node"},{"attributes":{},"tag":",","children":[","],"type":"node"},{"attributes":{},"tag":"Whitespace","children":[" "],"type":"node"},{"attributes":{},"tag":"Identifier","children":["v_"],"type":"node"},{"attributes":{},"tag":")","children":[")"],"type":"node"}],"type":"node"},{"attributes":{},"tag":"NewlineWs","children":["\n    "],"type":"node"}],"type":"node"},{"attributes":{},"tag":"end","children":["end"],"type":"node"}],"type":"node"},{"attributes":{},"tag":"NewlineWs","children":["\n"],"type":"node"}],"type":"node"},{"attributes":{},"tag":"end","children":["end"],"type":"node"}],"type":"node"},{"attributes":{},"tag":"NewlineWs","children":["\n"],"type":"node"},{"attributes":{},"tag":"NewlineWs","children":["\n"],"type":"node"},{"attributes":{},"tag":"=","children":[{"attributes":{},"tag":"call","children":[{"attributes":{"reftype":"symbol","document_id":"Pollen@localdeploy/ref/Pollen.SelectReference"},"tag":"reference","children":["SelectReference"],"type":"node"},{"attributes":{},"tag":"(","children":["("],"type":"node"},{"attributes":{},"tag":")","children":[")"],"type":"node"}],"type":"node"},{"attributes":{},"tag":"Whitespace","children":[" "],"type":"node"},{"attributes":{},"tag":"=","children":["="],"type":"node"},{"attributes":{},"tag":"call","children":[{"attributes":{},"tag":"Whitespace","children":[" "],"type":"node"},{"attributes":{},"tag":"call","children":[{"attributes":{"reftype":"symbol","document_id":"Pollen@localdeploy/ref/Pollen.SelectTag"},"tag":"reference","children":["SelectTag"],"type":"node"},{"attributes":{},"tag":"(","children":["("],"type":"node"},{"attributes":{},"tag":"quote","children":[{"attributes":{},"tag":":","children":[":"],"type":"node"},{"attributes":{},"tag":"Identifier","children":["reference"],"type":"node"}],"type":"node"},{"attributes":{},"tag":")","children":[")"],"type":"node"}],"type":"node"},{"attributes":{},"tag":"Whitespace","children":[" "],"type":"node"},{"attributes":{},"tag":"&","children":["&"],"type":"node"},{"attributes":{},"tag":"Whitespace","children":[" "],"type":"node"},{"attributes":{},"tag":"call","children":[{"attributes":{"reftype":"symbol","document_id":"Pollen@localdeploy/ref/Pollen.SelectHasAttr"},"tag":"reference","children":["SelectHasAttr"],"type":"node"},{"attributes":{},"tag":"(","children":["("],"type":"node"},{"attributes":{},"tag":"quote","children":[{"attributes":{},"tag":":","children":[":"],"type":"node"},{"attributes":{},"tag":"Identifier","children":["document_id"],"type":"node"}],"type":"node"},{"attributes":{},"tag":")","children":[")"],"type":"node"}],"type":"node"}],"type":"node"}],"type":"node"},{"attributes":{},"tag":"NewlineWs","children":["\n"],"type":"node"},{"attributes":{},"tag":"=","children":[{"attributes":{},"tag":"call","children":[{"attributes":{"reftype":"symbol","document_id":"Pollen@localdeploy/ref/Pollen.SelectSymbolReference"},"tag":"reference","children":["SelectSymbolReference"],"type":"node"},{"attributes":{},"tag":"(","children":["("],"type":"node"},{"attributes":{},"tag":")","children":[")"],"type":"node"}],"type":"node"},{"attributes":{},"tag":"Whitespace","children":[" "],"type":"node"},{"attributes":{},"tag":"=","children":["="],"type":"node"},{"attributes":{},"tag":"call","children":[{"attributes":{},"tag":"Whitespace","children":[" "],"type":"node"},{"attributes":{},"tag":"call","children":[{"attributes":{"reftype":"symbol","document_id":"Pollen@localdeploy/ref/Pollen.SelectReference"},"tag":"reference","children":["SelectReference"],"type":"node"},{"attributes":{},"tag":"(","children":["("],"type":"node"},{"attributes":{},"tag":")","children":[")"],"type":"node"}],"type":"node"},{"attributes":{},"tag":"Whitespace","children":[" "],"type":"node"},{"attributes":{},"tag":"&","children":["&"],"type":"node"},{"attributes":{},"tag":"Whitespace","children":[" "],"type":"node"},{"attributes":{},"tag":"call","children":[{"attributes":{"reftype":"symbol","document_id":"Pollen@localdeploy/ref/Pollen.SelectAttrEq"},"tag":"reference","children":["SelectAttrEq"],"type":"node"},{"attributes":{},"tag":"(","children":["("],"type":"node"},{"attributes":{},"tag":"quote","children":[{"attributes":{},"tag":":","children":[":"],"type":"node"},{"attributes":{},"tag":"Identifier","children":["reftype"],"type":"node"}],"type":"node"},{"attributes":{},"tag":",","children":[","],"type":"node"},{"attributes":{},"tag":"Whitespace","children":[" "],"type":"node"},{"attributes":{},"tag":"string","children":[{"attributes":{},"tag":"\"","children":["\""],"type":"node"},{"attributes":{},"tag":"String","children":["symbol"],"type":"node"},{"attributes":{},"tag":"\"","children":["\""],"type":"node"}],"type":"node"},{"attributes":{},"tag":")","children":[")"],"type":"node"}],"type":"node"}],"type":"node"}],"type":"node"},{"attributes":{},"tag":"NewlineWs","children":["\n"],"type":"node"},{"attributes":{},"tag":"=","children":[{"attributes":{},"tag":"call","children":[{"attributes":{"reftype":"symbol","document_id":"Pollen@localdeploy/ref/Pollen.SelectDocumentReference"},"tag":"reference","children":["SelectDocumentReference"],"type":"node"},{"attributes":{},"tag":"(","children":["("],"type":"node"},{"attributes":{},"tag":")","children":[")"],"type":"node"}],"type":"node"},{"attributes":{},"tag":"Whitespace","children":[" "],"type":"node"},{"attributes":{},"tag":"=","children":["="],"type":"node"},{"attributes":{},"tag":"call","children":[{"attributes":{},"tag":"Whitespace","children":[" "],"type":"node"},{"attributes":{},"tag":"call","children":[{"attributes":{"reftype":"symbol","document_id":"Pollen@localdeploy/ref/Pollen.SelectReference"},"tag":"reference","children":["SelectReference"],"type":"node"},{"attributes":{},"tag":"(","children":["("],"type":"node"},{"attributes":{},"tag":")","children":[")"],"type":"node"}],"type":"node"},{"attributes":{},"tag":"Whitespace","children":[" "],"type":"node"},{"attributes":{},"tag":"&","children":["&"],"type":"node"},{"attributes":{},"tag":"Whitespace","children":[" "],"type":"node"},{"attributes":{},"tag":"call","children":[{"attributes":{"reftype":"symbol","document_id":"Pollen@localdeploy/ref/Pollen.SelectAttrEq"},"tag":"reference","children":["SelectAttrEq"],"type":"node"},{"attributes":{},"tag":"(","children":["("],"type":"node"},{"attributes":{},"tag":"quote","children":[{"attributes":{},"tag":":","children":[":"],"type":"node"},{"attributes":{},"tag":"Identifier","children":["reftype"],"type":"node"}],"type":"node"},{"attributes":{},"tag":",","children":[","],"type":"node"},{"attributes":{},"tag":"Whitespace","children":[" "],"type":"node"},{"attributes":{},"tag":"string","children":[{"attributes":{},"tag":"\"","children":["\""],"type":"node"},{"attributes":{},"tag":"String","children":["document"],"type":"node"},{"attributes":{},"tag":"\"","children":["\""],"type":"node"}],"type":"node"},{"attributes":{},"tag":")","children":[")"],"type":"node"}],"type":"node"}],"type":"node"}],"type":"node"}],"type":"node"}],"type":"node"}],"type":"node"}],"type":"node"}