{"attributes":{"kind":"struct","backlinks":[{"tag":"documentation","title":"JupyterFormat","docid":"Pollen@pr-90/ref/Pollen.JupyterFormat"},{"tag":"sourcefile","title":"Pollen/formats/jupyter.jl","docid":"Pollen@pr-90/src/formats/jupyter.jl"},{"tag":"sourcefile","title":"Pollen/rewriters/references.jl","docid":"Pollen@pr-90/src/rewriters/references.jl"},{"tag":"sourcefile","title":"Pollen/formats/markdown.jl","docid":"Pollen@pr-90/src/formats/markdown.jl"},{"tag":"sourcefile","title":"Pollen/Pollen.jl","docid":"Pollen@pr-90/src/Pollen.jl"},{"tag":"sourcefile","title":"Pollen/rewriters/modulereference.jl","docid":"Pollen@pr-90/src/rewriters/modulereference.jl"},{"tag":"sourcefile","title":"Pollen/rewriters/sourcefiles.jl","docid":"Pollen@pr-90/src/rewriters/sourcefiles.jl"},{"tag":"document","title":"Working with documents","docid":"Pollen@pr-90/doc/docs/tutorials/documents.md"}],"methods":[{"symbol_id":"Pollen.MarkdownFormat","module_id":"Pollen","file":"formats/markdown.jl","line":12,"signature":"(::Signature)"},{"symbol_id":"Pollen.MarkdownFormat","module_id":"Pollen","file":"formats/markdown.jl","line":9,"signature":"(::Signature)"}],"package_id":"Pollen@pr-90","title":"MarkdownFormat","symbol_id":"Pollen.MarkdownFormat","exported":true,"module_id":"Pollen"},"tag":"documentation","children":[{"attributes":{"symbol":"Pollen.MarkdownFormat","line":1,"module":"Pollen","file":"formats/markdown.jl"},"tag":"docstring","children":[{"attributes":{},"tag":"md","children":[{"attributes":{"lang":""},"tag":"codeblock","children":["MarkdownFormat([parser]) <: Format\n"],"type":"node"},{"attributes":{},"tag":"p","children":["Format for reading CommonMark-compliant Markdown. See ",{"attributes":{"href":"https://github.com/MichaelHatherly/CommonMark.jl","title":""},"tag":"a","children":["CommonMark.jl"],"type":"node"}," for a reference."],"type":"node"}],"type":"node"}],"type":"node"}],"type":"node"}