{"attributes":{"kind":"function","backlinks":[{"tag":"sourcefile","title":"Pollen/rewriters/backlinks.jl","docid":"Pollen@localdeploy/src/rewriters/backlinks.jl"}],"methods":[{"symbol_id":"Pollen.SelectSymbolReference","module_id":"Pollen","file":"rewriters/backlinks.jl","line":73,"signature":"(::Signature)"}],"package_id":"Pollen@localdeploy","title":"SelectSymbolReference","symbol_id":"Pollen.SelectSymbolReference","exported":false,"module_id":"Pollen"},"tag":"documentation","children":[],"type":"node"}